<rights xmlns="http://www.loc.gov/premis/v3" version="3.0">
	<rightsStatement>
		<rightsStatementIdentifier>
			<rightsStatementIdentifierType valueURI="http://id.loc.gov/vocabulary/identifiers/local">local</rightsStatementIdentifierType>
			<rightsStatementIdentifierValue>access-master</rightsStatementIdentifierValue>
		</rightsStatementIdentifier>
		<rightsBasis valueURI="http://id.loc.gov/vocabulary/preservation/rightsBasis/sta">statute</rightsBasis>
		<statuteInformation>
			<statuteJurisdiction authority="ISO 3166-2:US">US-NC</statuteJurisdiction>
			<statuteCitation>G.S. 132</statuteCitation>
			<statuteDocumentationIdentifier>
				<statuteDocumentationIdentifierType valueURI="http://id.loc.gov/vocabulary/identifiers/uri">Uniform Resource Identifier</statuteDocumentationIdentifierType>
				<statuteDocumentationIdentifierValue>http://www.ncleg.net/gascripts/statutes/statutelookup.pl?statute=132</statuteDocumentationIdentifierValue>
				<statuteDocumentationRole>law</statuteDocumentationRole>
			</statuteDocumentationIdentifier>
		</statuteInformation>
		<rightsGranted>
			<act valueURI="http://id.loc.gov/vocabulary/preservation/actionsGranted/dis">disseminate</act>
			<rightsGrantedNote>Attribution statement: "Courtesy of the North Carolina Department of Natural and Cultural Resources."</rightsGrantedNote>
		</rightsGranted>
		<linkingObjectIdentifier>
			<linkingObjectIdentifierType valueURI="http://id.loc.gov/vocabulary/identifiers/local">local</linkingObjectIdentifierType>
			<linkingObjectIdentifierValue>{root/EAXS_file}_tagged</linkingObjectIdentifierValue>
		</linkingObjectIdentifier>
	</rightsStatement>
</rights>

